nncodec/__init__.py
nncodec/fl.py
nncodec/nn.py
nncodec/tensor.py
nncodec/extensions/__init__.py
nncodec/extensions/deepCABAC.cpython-39-darwin.so
nncodec/extensions/deepCABAC/source/bindings.cpp
nncodec/extensions/deepCABAC/source/Lib/CommonLib/ContextModel.cpp
nncodec/extensions/deepCABAC/source/Lib/CommonLib/ContextModel.h
nncodec/extensions/deepCABAC/source/Lib/CommonLib/ContextModeler.cpp
nncodec/extensions/deepCABAC/source/Lib/CommonLib/ContextModeler.h
nncodec/extensions/deepCABAC/source/Lib/CommonLib/HdspOpts.h
nncodec/extensions/deepCABAC/source/Lib/CommonLib/Quant.cpp
nncodec/extensions/deepCABAC/source/Lib/CommonLib/Quant.h
nncodec/extensions/deepCABAC/source/Lib/CommonLib/Scan.h
nncodec/extensions/deepCABAC/source/Lib/CommonLib/TypeDef.h
nncodec/extensions/deepCABAC/source/Lib/DecLib/BinDecoder.cpp
nncodec/extensions/deepCABAC/source/Lib/DecLib/BinDecoder.h
nncodec/extensions/deepCABAC/source/Lib/DecLib/CABACDecoder.cpp
nncodec/extensions/deepCABAC/source/Lib/DecLib/CABACDecoder.h
nncodec/extensions/deepCABAC/source/Lib/EncLib/BinEncoder.cpp
nncodec/extensions/deepCABAC/source/Lib/EncLib/BinEncoder.h
nncodec/extensions/deepCABAC/source/Lib/EncLib/CABACEncoder.cpp
nncodec/extensions/deepCABAC/source/Lib/EncLib/CABACEncoder.h
nncodec/framework/__init__.py
nncodec/framework/applications/__init__.py
nncodec/framework/applications/settings.py
nncodec/framework/applications/datasets/Berlin_V2X.py
nncodec/framework/applications/datasets/__init__.py
nncodec/framework/applications/datasets/cifar.py
nncodec/framework/applications/datasets/imagenet.py
nncodec/framework/applications/datasets/voc2012.py
nncodec/framework/applications/models/ResNet_CIFAR.py
nncodec/framework/applications/models/__init__.py
nncodec/framework/applications/models/tinyllama.py
nncodec/framework/applications/models/tokenizer.py
nncodec/framework/applications/utils/__init__.py
nncodec/framework/applications/utils/evaluation.py
nncodec/framework/applications/utils/metrics.py
nncodec-2.0.4.dist-info/METADATA
nncodec-2.0.4.dist-info/WHEEL
nncodec-2.0.4.dist-info/top_level.txt
nncodec-2.0.4.dist-info/RECORD
