Metadata-Version: 2.4
Name: nncodec
Version: 2.0.4
Summary: Fraunhofer HHI implementation of the Neural Network Coding (NNC) Standard
Home-page: https://hhi.fraunhofer.de
Author: Paul Haase, Daniel Becking
Author-email: paul.haase@hhi.fraunhofer.de, daniel.becking@hhi.fraunhofer.de
License: BSD
Requires-Python: >=3.8
Requires-Dist: Click>=7.0
Requires-Dist: scikit-learn>=0.23.1
Requires-Dist: tqdm>=4.32.2
Requires-Dist: h5py>=3.1.0
Requires-Dist: pybind11>=2.6.2
Requires-Dist: pandas>=1.0.5
Requires-Dist: opencv-python>=4.4.0.46
Requires-Dist: torch>=2
Requires-Dist: torchvision>=0.16
Requires-Dist: wandb>=0.15.3
Requires-Dist: ptflops>=0.7
Requires-Dist: matplotlib>=3.7.1
Requires-Dist: torchmetrics>=0.11.4
Requires-Dist: flwr[simulation]>=1.5
Requires-Dist: hydra-core>=1.3.2
Requires-Dist: sentencepiece>=0.1.99
Requires-Dist: numpy<2
Dynamic: author
Dynamic: author-email
Dynamic: description
Dynamic: description-content-type
Dynamic: home-page
Dynamic: license
Dynamic: requires-dist
Dynamic: requires-python
Dynamic: summary
